[{"filter_paths":["immigration enforcement","vans"],"id":"vans","desc":"immigration enforcement","mode":"FILTER"},{"filter_paths":["solidarity work"],"id":"solidarity work","desc":"solidarity work","mode":"CATEGORY"},{"filter_paths":["immigration enforcement","police presence"],"id":"police presence","desc":"immigration enforcement","mode":"FILTER"},{"filter_paths":["immigration enforcement","raids"],"id":"raids","desc":"immigration enforcement","mode":"FILTER"},{"filter_paths":["immigration enforcement","surveillance tech"],"id":"surveillance tech","desc":"immigration enforcement","mode":"FILTER"},{"filter_paths":["misc","far right presence"],"id":"far right presence","desc":"misc","mode":"FILTER"},{"filter_paths":["enforcement"],"id":"enforcement","desc":"enforcement","mode":"CATEGORY"}]